LICENSE
pyproject.toml
rubric_trec_rag/__init__.py
rubric_trec_rag/build_rag_segment_index.py
rubric_trec_rag/convert_trec_rag_output.py
rubric_trec_rag/export_rag_gen_as_run.py
rubric_trec_rag/rag_generation_inputs.py
rubric_trec_rag/rag_retrieval_inputs.py
rubric_trec_rag/segment_index.py
rubric_trec_rag.egg-info/PKG-INFO
rubric_trec_rag.egg-info/SOURCES.txt
rubric_trec_rag.egg-info/dependency_links.txt
rubric_trec_rag.egg-info/requires.txt
rubric_trec_rag.egg-info/top_level.txt